byusi_dlb-0.2.0.dist-info/licenses/LICENSE
dlb/__init__.py
dlb/cli.py
dlb/config.py
dlb/core.py
dlb/i18n.py
byusi_dlb-0.2.0.dist-info/METADATA
byusi_dlb-0.2.0.dist-info/WHEEL
byusi_dlb-0.2.0.dist-info/entry_points.txt
byusi_dlb-0.2.0.dist-info/top_level.txt
byusi_dlb-0.2.0.dist-info/RECORD
